ros_rosidl_adapter-4.9.5.data/data/lib/python3.13/site-packages/rosidl_adapter/__init__.py
ros_rosidl_adapter-4.9.5.data/data/lib/python3.13/site-packages/rosidl_adapter/__main__.py
ros_rosidl_adapter-4.9.5.data/data/lib/python3.13/site-packages/rosidl_adapter/cli.py
ros_rosidl_adapter-4.9.5.data/data/lib/python3.13/site-packages/rosidl_adapter/main.py
ros_rosidl_adapter-4.9.5.data/data/lib/python3.13/site-packages/rosidl_adapter/parser.py
ros_rosidl_adapter-4.9.5.data/data/lib/python3.13/site-packages/rosidl_adapter/py.typed
ros_rosidl_adapter-4.9.5.data/data/lib/python3.13/site-packages/rosidl_adapter/__pycache__/__init__.cpython-313.pyc
ros_rosidl_adapter-4.9.5.data/data/lib/python3.13/site-packages/rosidl_adapter/__pycache__/__main__.cpython-313.pyc
ros_rosidl_adapter-4.9.5.data/data/lib/python3.13/site-packages/rosidl_adapter/__pycache__/cli.cpython-313.pyc
ros_rosidl_adapter-4.9.5.data/data/lib/python3.13/site-packages/rosidl_adapter/__pycache__/main.cpython-313.pyc
ros_rosidl_adapter-4.9.5.data/data/lib/python3.13/site-packages/rosidl_adapter/__pycache__/parser.cpython-313.pyc
ros_rosidl_adapter-4.9.5.data/data/lib/python3.13/site-packages/rosidl_adapter/action/__init__.py
ros_rosidl_adapter-4.9.5.data/data/lib/python3.13/site-packages/rosidl_adapter/action/__pycache__/__init__.cpython-313.pyc
ros_rosidl_adapter-4.9.5.data/data/lib/python3.13/site-packages/rosidl_adapter/msg/__init__.py
ros_rosidl_adapter-4.9.5.data/data/lib/python3.13/site-packages/rosidl_adapter/msg/__pycache__/__init__.cpython-313.pyc
ros_rosidl_adapter-4.9.5.data/data/lib/python3.13/site-packages/rosidl_adapter/resource/__init__.py
ros_rosidl_adapter-4.9.5.data/data/lib/python3.13/site-packages/rosidl_adapter/resource/action.idl.em
ros_rosidl_adapter-4.9.5.data/data/lib/python3.13/site-packages/rosidl_adapter/resource/msg.idl.em
ros_rosidl_adapter-4.9.5.data/data/lib/python3.13/site-packages/rosidl_adapter/resource/srv.idl.em
ros_rosidl_adapter-4.9.5.data/data/lib/python3.13/site-packages/rosidl_adapter-4.9.5-py3.13.egg-info/PKG-INFO
ros_rosidl_adapter-4.9.5.data/data/lib/python3.13/site-packages/rosidl_adapter-4.9.5-py3.13.egg-info/SOURCES.txt
ros_rosidl_adapter-4.9.5.data/data/lib/python3.13/site-packages/rosidl_adapter-4.9.5-py3.13.egg-info/dependency_links.txt
ros_rosidl_adapter-4.9.5.data/data/lib/python3.13/site-packages/rosidl_adapter-4.9.5-py3.13.egg-info/entry_points.txt
ros_rosidl_adapter-4.9.5.data/data/lib/python3.13/site-packages/rosidl_adapter-4.9.5-py3.13.egg-info/top_level.txt
ros_rosidl_adapter-4.9.5.dist-info/METADATA
ros_rosidl_adapter-4.9.5.dist-info/WHEEL
ros_rosidl_adapter-4.9.5.dist-info/entry_points.txt
ros_rosidl_adapter-4.9.5.dist-info/top_level.txt
ros_rosidl_adapter-4.9.5.dist-info/RECORD
