Metadata-Version: 2.4
Name: ros-rosidl-adapter
Version: 4.9.5
Summary: Wheel for the rosidl_adapter (ros-rosidl-adapter) ROS 2 package.
Requires-Dist: ros-rosidl-cli~=4.9.5
Requires-Dist: empy
Dynamic: description
Dynamic: description-content-type
Dynamic: requires-dist
Dynamic: summary
